[
  {
    "id": "06392d6f29a8afa0",
    "title": "Clinical outcomes and spatial transcriptomic profiles of CD19/20 CAR-T therapy in relapsed or refractory B-cell non-Hodgkin's lymphoma.",
    "url": "https://pubmed.ncbi.nlm.nih.gov/42144261",
    "canonicalUrl": "https://pubmed.ncbi.nlm.nih.gov/42144261",
    "source": "pubmed",
    "publicationName": "Journal for immunotherapy of cancer",
    "journalName": "Journal for immunotherapy of cancer",
    "publishedAt": "2026-05-17T00:00:00.000Z",
    "fetchedAt": "2026-05-19T16:12:33.430Z",
    "snippet": "Relapsed or refractory (R/R) B-cell non-Hodgkin's lymphoma (B-NHL) remains a major therapeutic challenge despite CD19-directed chimeric antigen receptor (CAR) T-cell therapies, with treatment failure often driven by antigen escape and limited CAR-T persistence. Dual targeting of CD19 and CD20 may mitigate antigen loss. We conducted an expanded phase I/II st...",
    "tags": [
      "research",
      "pubmed",
      "Spatial oncology",
      "spatial transcriptomics",
      "cancer",
      "spatial"
    ],
    "topicBuckets": [
      "spatial",
      "oncology",
      "computational biology",
      "ai",
      "gene therapy",
      "translational medicine",
      "immunology"
    ],
    "isNewToday": false,
    "importanceScore": 82,
    "importanceSignals": [
      "recent",
      "priority topic: oncology, computational biology",
      "high-signal source",
      "rich summary",
      "rich metadata"
    ],
    "isFeatured": true
  }
]
