[
  {
    "id": "19d65b9109938a74",
    "title": "FDA bolsters bespoke therapy framework with new draft safety guidelines",
    "url": "https://www.biospace.com/drug-development/fda-bolsters-bespoke-therapy-framework-with-new-draft-safety-guidelines",
    "canonicalUrl": "https://www.biospace.com/drug-development/fda-bolsters-bespoke-therapy-framework-with-new-draft-safety-guidelines",
    "source": "biospace",
    "publicationName": "BioSpace",
    "publishedAt": "2026-04-14T18:30:03.000Z",
    "fetchedAt": "2026-04-16T14:31:28.407Z",
    "snippet": "The draft guidance supports the agency’s new pathway designed to speed up the development of custom gene therapies.",
    "tags": [
      "biotech",
      "industry"
    ],
    "topicBuckets": [
      "biotech"
    ],
    "isNewToday": false,
    "importanceScore": 54,
    "importanceSignals": [
      "very recent",
      "rich metadata"
    ],
    "isFeatured": false
  },
  {
    "id": "86737d3985d7e719",
    "title": "50 employees impacted as Astellas closes Universal Cells' Seattle office",
    "url": "https://www.biospace.com/job-trends/50-employees-impacted-as-astellas-closes-universal-cells-seattle-office",
    "canonicalUrl": "https://www.biospace.com/job-trends/50-employees-impacted-as-astellas-closes-universal-cells-seattle-office",
    "source": "biospace",
    "publicationName": "BioSpace",
    "publishedAt": "2026-04-14T15:16:08.000Z",
    "fetchedAt": "2026-04-16T14:31:28.407Z",
    "snippet": "By closing the Universal Cells Seattle location, Astellas is reportedly consolidating cell therapy, gene therapy and oncology research at its South San Francisco, California, and Westborough, Massachusetts, sites.",
    "tags": [
      "biotech",
      "industry"
    ],
    "topicBuckets": [
      "biotech",
      "oncology",
      "gene therapy"
    ],
    "isNewToday": false,
    "importanceScore": 80,
    "importanceSignals": [
      "very recent",
      "priority topic: oncology, gene therapy",
      "rich summary",
      "rich metadata"
    ],
    "isFeatured": true
  },
  {
    "id": "265bfc61b88cb466",
    "title": "Bonus: Q1 2026 Job Market Update",
    "url": "https://www.biospace.com/job-trends/bonus-q1-2026-job-market-update",
    "canonicalUrl": "https://www.biospace.com/job-trends/bonus-q1-2026-job-market-update",
    "source": "biospace",
    "publicationName": "BioSpace",
    "publishedAt": "2026-04-14T14:37:31.000Z",
    "fetchedAt": "2026-04-16T14:31:28.407Z",
    "snippet": "In this bonus episode, BioSpace’s Vice President of Marketing ⁠Chantal Dresner⁠ and Careers Editor ⁠Angela Gabriel⁠ take a look at Q1 job market performance and what it signals for the coming months.",
    "tags": [
      "biotech",
      "industry"
    ],
    "topicBuckets": [
      "biotech"
    ],
    "isNewToday": false,
    "importanceScore": 60,
    "importanceSignals": [
      "very recent",
      "rich summary",
      "rich metadata"
    ],
    "isFeatured": false
  },
  {
    "id": "5f36a550567ec95f",
    "title": "With nearly a quarter billion in Q1, J&J targets $100B revenue in 2026",
    "url": "https://www.biospace.com/business/with-nearly-a-quarter-billion-in-q1-j-j-targets-100b-revenue-in-2026",
    "canonicalUrl": "https://www.biospace.com/business/with-nearly-a-quarter-billion-in-q1-j-j-targets-100b-revenue-in-2026",
    "source": "biospace",
    "publicationName": "BioSpace",
    "publishedAt": "2026-04-14T14:31:39.000Z",
    "fetchedAt": "2026-04-16T14:31:28.407Z",
    "snippet": "With robust sales performance from oncology darling Darzalex and immunology superstar Tremfya, Johnson & Johnson is “off to a fast start in 2026,” CEO Joaquin Duato told investors on Tuesday.",
    "tags": [
      "biotech",
      "industry"
    ],
    "topicBuckets": [
      "biotech",
      "oncology",
      "immunology"
    ],
    "isNewToday": false,
    "importanceScore": 60,
    "importanceSignals": [
      "recent",
      "priority topic: oncology",
      "rich summary",
      "rich metadata"
    ],
    "isFeatured": false
  },
  {
    "id": "c5c8de1c7c4da458",
    "title": "IL-13R&#x3b1;2 in liver cancer: Endothelial target for precision therapy.",
    "url": "https://pubmed.ncbi.nlm.nih.gov/41985329",
    "canonicalUrl": "https://pubmed.ncbi.nlm.nih.gov/41985329",
    "source": "pubmed",
    "publicationName": "Biomedicine & pharmacotherapy = Biomedecine & pharmacotherapie",
    "journalName": "Biomedicine & pharmacotherapy = Biomedecine & pharmacotherapie",
    "publishedAt": "2026-04-14T00:00:00.000Z",
    "fetchedAt": "2026-04-16T14:31:29.308Z",
    "snippet": "Hepatocellular carcinoma (HCC) remains a leading cause of cancer-related mortality worldwide, and durable responses to current systemic therapies is still limited. Tumor-associated endothelial cells (TECs) actively shape the immunosuppressive tumor microenvironment and contribute to therapeutic resistance, yet they remain underexploited as therapeutic targe...",
    "tags": [
      "research",
      "pubmed",
      "Single-cell TME",
      "single-cell",
      "tumor microenvironment"
    ],
    "topicBuckets": [
      "single-cell",
      "oncology",
      "immunology",
      "ai"
    ],
    "isNewToday": false,
    "importanceScore": 72,
    "importanceSignals": [
      "recent",
      "priority topic: oncology, ai",
      "high-signal source",
      "rich summary",
      "rich metadata"
    ],
    "isFeatured": true
  },
  {
    "id": "6af52e955cc967db",
    "title": "Intravitreal photoswitch therapy in advanced retinitis pigmentosa: a phase 1 open-label trial.",
    "url": "https://pubmed.ncbi.nlm.nih.gov/41981307",
    "canonicalUrl": "https://pubmed.ncbi.nlm.nih.gov/41981307",
    "source": "pubmed",
    "publicationName": "Nature medicine",
    "journalName": "Nature medicine",
    "publishedAt": "2026-04-14T00:00:00.000Z",
    "fetchedAt": "2026-04-16T14:31:29.308Z",
    "snippet": "A small azobenzene photoswitch molecule (KIO-301), designed to confer light responsiveness to retinal ganglion cells, was evaluated for safety and feasibility in a first-in-human, phase 1, gene-agnostic, open-label, dose-escalation clinical trial in individuals with advanced retinitis pigmentosa (RP). KIO-301 was administered by intravitreal injection to 12...",
    "tags": [
      "research",
      "pubmed",
      "Gene therapy inflammation",
      "gene therapy",
      "mRNA delivery",
      "inflammation"
    ],
    "topicBuckets": [
      "gene therapy",
      "immunology",
      "biotech",
      "translational medicine"
    ],
    "isNewToday": false,
    "importanceScore": 72,
    "importanceSignals": [
      "recent",
      "priority topic: gene therapy, translational medicine",
      "high-signal source",
      "rich summary",
      "rich metadata"
    ],
    "isFeatured": true
  },
  {
    "id": "2e5aee4d4cf552c0",
    "title": "Integrated spatial and single&#x2011;cell transcriptomics maps disulfidptosis in renal cell carcinoma and reveals PDLIM1 as a prognostic biomarker and potential therapeutic target.",
    "url": "https://pubmed.ncbi.nlm.nih.gov/41985321",
    "canonicalUrl": "https://pubmed.ncbi.nlm.nih.gov/41985321",
    "source": "pubmed",
    "publicationName": "Translational oncology",
    "journalName": "Translational oncology",
    "publishedAt": "2026-04-14T00:00:00.000Z",
    "fetchedAt": "2026-04-16T14:31:29.308Z",
    "snippet": "Disulfidptosis is a regulated cell death program linked to redox stress, metabolism, and the actin cytoskeleton. Its organization in tissue and clinical relevance in renal cell carcinoma are not well defined. We integrated spatial transcriptomics from six renal cancer sections with four single cell RNA sequencing cohorts. Disulfidptosis scores were computed...",
    "tags": [
      "research",
      "pubmed",
      "Spatial oncology",
      "spatial transcriptomics",
      "cancer",
      "biomarker",
      "spatial"
    ],
    "topicBuckets": [
      "spatial",
      "oncology",
      "computational biology",
      "single-cell",
      "translational medicine"
    ],
    "isNewToday": false,
    "importanceScore": 82,
    "importanceSignals": [
      "recent",
      "priority topic: oncology, computational biology",
      "high-signal source",
      "rich summary",
      "rich metadata"
    ],
    "isFeatured": true
  },
  {
    "id": "007148de6ff2ab9b",
    "title": "Blockage of cuproplasia inhibits pancreatic tumour-associated neutrophils infiltration through TRAF6/STAT3/CCL2 pathway.",
    "url": "https://pubmed.ncbi.nlm.nih.gov/41981139",
    "canonicalUrl": "https://pubmed.ncbi.nlm.nih.gov/41981139",
    "source": "pubmed",
    "publicationName": "British journal of cancer",
    "journalName": "British journal of cancer",
    "publishedAt": "2026-04-14T00:00:00.000Z",
    "fetchedAt": "2026-04-16T14:31:29.308Z",
    "snippet": "Pancreatic ductal adenocarcinoma (PDAC) is a highly aggressive cancer with a poor prognosis and is easy to developing drug resistance to conventional therapies due to its distinctive tumour microenvironment. Recent advancements have brought attention to the aberrant copper metabolism in this malignancy, but the influence of intracellular cuproplasia and bal...",
    "tags": [
      "research",
      "pubmed",
      "Spatial oncology",
      "spatial transcriptomics",
      "cancer"
    ],
    "topicBuckets": [
      "spatial",
      "oncology",
      "computational biology"
    ],
    "isNewToday": false,
    "importanceScore": 72,
    "importanceSignals": [
      "recent",
      "priority topic: oncology, computational biology",
      "high-signal source",
      "rich summary",
      "rich metadata"
    ],
    "isFeatured": true
  },
  {
    "id": "d337ba5373391bb3",
    "title": "Spatial transcriptomics of en bloc transurethral resection of bladder tumor specimens defines an invasive-front gene expression signature.",
    "url": "https://pubmed.ncbi.nlm.nih.gov/41981124",
    "canonicalUrl": "https://pubmed.ncbi.nlm.nih.gov/41981124",
    "source": "pubmed",
    "publicationName": "NPJ precision oncology",
    "journalName": "NPJ precision oncology",
    "publishedAt": "2026-04-14T00:00:00.000Z",
    "fetchedAt": "2026-04-16T14:31:29.308Z",
    "snippet": "Bladder cancer is classified by depth of invasion into muscle-invasive bladder cancer (MIBC) and non-muscle-invasive bladder cancer (NMIBC). Because some NMIBC cases progress to MIBC, it is important to elucidate the mechanisms of invasion. Spatial transcriptomics is a powerful tool for characterizing the tumor microenvironment. We applied Visium to seven h...",
    "tags": [
      "research",
      "pubmed",
      "Spatial oncology",
      "spatial transcriptomics",
      "cancer",
      "spatial"
    ],
    "topicBuckets": [
      "spatial",
      "oncology",
      "computational biology"
    ],
    "isNewToday": false,
    "importanceScore": 72,
    "importanceSignals": [
      "recent",
      "priority topic: oncology, computational biology",
      "high-signal source",
      "rich summary",
      "rich metadata"
    ],
    "isFeatured": true
  }
]
