[
  {
    "id": "af28f72215cf9f5b",
    "title": "Breast cancer risk genes affecting individual radiosensitivity.",
    "url": "https://pubmed.ncbi.nlm.nih.gov/42289459",
    "canonicalUrl": "https://pubmed.ncbi.nlm.nih.gov/42289459",
    "source": "pubmed",
    "publicationName": "Scientific reports",
    "journalName": "Scientific reports",
    "publishedAt": "2026-06-14T00:00:00.000Z",
    "fetchedAt": "2026-06-15T17:46:33.375Z",
    "snippet": "Increased radiosensitivity can cause adverse radiotherapy effects. Heterozygote variants in breast cancer risk genes increase cancer risk and may affect radiosensitivity. This study assessed their impact on individual radiosensitivity to determine the radiation risk for gene carriers. Radiosensitivity was analyzed in 273 patients with breast cancer risk gen...",
    "tags": [
      "research",
      "pubmed",
      "Spatial oncology",
      "spatial transcriptomics",
      "cancer"
    ],
    "topicBuckets": [
      "spatial",
      "oncology",
      "computational biology"
    ],
    "isNewToday": false,
    "importanceScore": 82,
    "importanceSignals": [
      "very recent",
      "priority topic: oncology, computational biology",
      "high-signal source",
      "rich summary",
      "rich metadata"
    ],
    "isFeatured": true
  }
]
